<?xml version="1.0" encoding="utf-8"?>
<CallableObject guid="34fc854d-e39e-43f9-9a1d-031056d0a571" name="NBitcoin.deriveAddressFromExtPubKeyUnitTestData" description="derive Address From Ext Pub Key Unit Test Data" namespace="GeneXus.Programs">
  <Signature name="parm">
    <Parameter name="ReturnValue" accessor="out" collection="true">
      <Field name="deriveAddressFromExtPubKeyUnitTestSDT" description="derive Address From Ext Pub Key Unit Test SDT">
        <Fields>
          <Field name="TestCaseId" description="Test case identifier">
            <Properties>
              <Property>
                <Name>Type</Name>
                <Value>VarChar</Value>
              </Property>
              <Property>
                <Name>Length</Name>
                <Value>40</Value>
              </Property>
            </Properties>
          </Field>
          <Field name="deserializedExtPubKey" description="">
            <Properties>
              <Property>
                <Name>Type</Name>
                <Value>Character</Value>
              </Property>
              <Property>
                <Name>Length</Name>
                <Value>250</Value>
              </Property>
            </Properties>
          </Field>
          <Field name="base" description="">
            <Properties>
              <Property>
                <Name>Type</Name>
                <Value>Numeric</Value>
              </Property>
              <Property>
                <Name>Length</Name>
                <Value>10</Value>
              </Property>
              <Property>
                <Name>Picture</Name>
                <Value>ZZZZZZZZZ9</Value>
              </Property>
            </Properties>
          </Field>
          <Field name="start" description="">
            <Properties>
              <Property>
                <Name>Type</Name>
                <Value>Numeric</Value>
              </Property>
              <Property>
                <Name>Length</Name>
                <Value>10</Value>
              </Property>
              <Property>
                <Name>Picture</Name>
                <Value>ZZZZZZZZZ9</Value>
              </Property>
            </Properties>
          </Field>
          <Field name="end" description="">
            <Properties>
              <Property>
                <Name>Type</Name>
                <Value>Numeric</Value>
              </Property>
              <Property>
                <Name>Length</Name>
                <Value>10</Value>
              </Property>
              <Property>
                <Name>Picture</Name>
                <Value>ZZZZZZZZZ9</Value>
              </Property>
            </Properties>
          </Field>
          <Field name="sdt_addressess" description="">
            <Fields>
              <Field name="Address" description="Address" collection="true">
                <Properties>
                  <Property>
                    <Name>Type</Name>
                    <Value>Character</Value>
                  </Property>
                  <Property>
                    <Name>Length</Name>
                    <Value>250</Value>
                  </Property>
                </Properties>
              </Field>
            </Fields>
          </Field>
          <Field name="Expectedsdt_addressess" description="">
            <Fields>
              <Field name="Address" description="Address" collection="true">
                <Properties>
                  <Property>
                    <Name>Type</Name>
                    <Value>Character</Value>
                  </Property>
                  <Property>
                    <Name>Length</Name>
                    <Value>250</Value>
                  </Property>
                </Properties>
              </Field>
            </Fields>
          </Field>
          <Field name="Msgsdt_addressess" description="Message to show for assertion over field sdt_addressess">
            <Properties>
              <Property>
                <Name>Type</Name>
                <Value>VarChar</Value>
              </Property>
              <Property>
                <Name>Length</Name>
                <Value>100</Value>
              </Property>
            </Properties>
          </Field>
          <Field name="error" description="">
            <Properties>
              <Property>
                <Name>Type</Name>
                <Value>Character</Value>
              </Property>
              <Property>
                <Name>Length</Name>
                <Value>200</Value>
              </Property>
            </Properties>
          </Field>
          <Field name="Expectederror" description="">
            <Properties>
              <Property>
                <Name>Type</Name>
                <Value>Character</Value>
              </Property>
              <Property>
                <Name>Length</Name>
                <Value>200</Value>
              </Property>
            </Properties>
          </Field>
          <Field name="Msgerror" description="Message to show for assertion over field error">
            <Properties>
              <Property>
                <Name>Type</Name>
                <Value>VarChar</Value>
              </Property>
              <Property>
                <Name>Length</Name>
                <Value>100</Value>
              </Property>
            </Properties>
          </Field>
        </Fields>
      </Field>
    </Parameter>
  </Signature>
</CallableObject>